<?xml version="1.0"?>
<formations>
    <formation>
        <titre>aaaaaaaaaaaaaaa</titre>
        <date_debut>2023-05-31</date_debut>
        <date_fin>2023-06-27</date_fin>
        <description>aaaaaaaaaaaaaaaaaaa</description>
    </formation>
    <formation>
        <titre>eeazeae</titre>
        <date_debut>2023-06-07</date_debut>
        <date_fin>2023-06-21</date_fin>
        <description>zaeazeaz</description>
    </formation>
    <formation>
        <titre>eeaea</titre>
        <date_debut>2023-06-15</date_debut>
        <date_fin>2023-06-16</date_fin>
        <description>eaeeaeaea</description>
    </formation>
    <formation>
        <titre>eazeazeaze</titre>
        <date_debut>2023-06-01</date_debut>
        <date_fin>2023-06-16</date_fin>
        <description>eazeazeazeaz</description>
    </formation>
    <formation>
        <titre>dzada</titre>
        <date_debut>2023-06-16</date_debut>
        <date_fin>2023-06-22</date_fin>
        <description>dazdada</description>
    </formation>
    <formation>
        <titre/>
        <date_debut/>
        <date_fin/>
        <description/>
    </formation>
    <formation>
        <titre>helloooooooo</titre>
        <date_debut>2023-06-02</date_debut>
        <date_fin>2023-06-02</date_fin>
        <description>
            heloooooooooooooooooooooooooooooooooooooooooooooooooooooooooooooooooooooooooooooooooooooooooooooooooo</description>
    </formation>
    <formation>
        <titre>grgegeg</titre>
        <date_debut>2023-06-10</date_debut>
        <date_fin>2023-06-02</date_fin>
        <description>dadadadazda</description>
    </formation>
    <formation>
        <titre>rg"'egzeg</titre>
        <date_debut>2023-06-22</date_debut>
        <date_fin>2023-06-07</date_fin>
        <description>eazeaeaea</description>
    </formation>
    <formation>
        <titre>sas</titre>
        <date_debut>2023-06-01</date_debut>
        <date_fin>2023-06-23</date_fin>
        <description>saaaaaaaaaaa</description>
    </formation>
    <formation>
        <titre>stage</titre>
        <date_debut>2023-06-08</date_debut>
        <date_fin>2023-06-10</date_fin>
        <description>stage</description>
    </formation>
    <formation>
        <titre>bbbbbbbbbbbbbbbbb</titre>
        <date_debut>2023-06-25</date_debut>
        <date_fin>2023-07-23</date_fin>
        <description>bbbbbbbbbbbbbbbb</description>
    </formation>
    <formation>
        <titre>ttttttttttttttttttttt</titre>
        <date_debut>2023-06-25</date_debut>
        <date_fin>2023-07-14</date_fin>
        <description>tttttttttttttttttttttt</description>
    </formation>
    <formation>
        <titre>nnnnnnnnnnnnnnnnn</titre>
        <date_debut>2023-06-02</date_debut>
        <date_fin>2023-08-20</date_fin>
        <description>nnnnnnnnnnnnnnnnnnnnnn</description>
    </formation>
    <formation>
        <titre>squeezie</titre>
        <date_debut>2023-06-14</date_debut>
        <date_fin>2023-09-15</date_fin>
        <description>yo</description>
    </formation>
    <formation>
        <titre>Stage chez Renault</titre>
        <date_debut>2023-06-13</date_debut>
        <date_fin>2024-01-10</date_fin>
        <description>cool</description>
    </formation>
    <formation>
        <titre>d</titre>
        <date_debut>2023-05-31</date_debut>
        <date_fin>2023-06-24</date_fin>
        <description>ddde</description>
    </formation>
<formation><titre>premiere alej</titre><date_debut>2023-06-07</date_debut><date_fin>2023-06-24</date_fin><description>C'&#xE9;tait cool</description></formation><formation><titre>premiere alej</titre><date_debut>2023-06-07</date_debut><date_fin>2023-06-24</date_fin><description>C'&#xE9;tait cool</description></formation></formations>
